nlpmining.py
nlpmining-0.0.5.dist-info/LICENSE.txt
nlpmining-0.0.5.dist-info/METADATA
nlpmining-0.0.5.dist-info/WHEEL
nlpmining-0.0.5.dist-info/top_level.txt
nlpmining-0.0.5.dist-info/RECORD
