Metadata-Version: 2.1
Name: nlpmining
Version: 0.0.5
Summary: Text Preprocessing  package
Author: NLP Mining
Classifier: Programming Language :: Python :: 3
Classifier: License :: OSI Approved :: MIT License
Classifier: Operating System :: OS Independent
Requires-Python: >=3.6
License-File: LICENSE.txt
Requires-Dist: pandas
Requires-Dist: numpy
